{"blocks":[{"text":"용접은 감전, 아크광·화상, 흄·가스, 화재·폭발, 고압가스용기, 소음, 중량물·추락과 연삭기 위험이 겹치는 작업이다. 작업명만으로 평가하지 말고 재료·도료, 장소, 자세, 주변 가연물, 환기, 동시작업과 비상대피까지 확인한다. 위험성평가는 유해·위험요인 파악 → 위험성 결정 → 감소대책 수립·실행 → 효과 확인·공유로 이어진다. 대책은 제거 → 대체 → 공학적 대책 → 관리적 대책 → 개인보호구 순으로 우선한다. 예컨대 유해도료 제거·저유해 공정 대체, 국소배기·차폐·인터록, 작업허가·교육, 호흡보호구 순으로 겹겹이 통제한다. 보호구만 지급하고 환기·격리를 생략해서는 안 된다. 「산업안전보건법」 제36조와 2026년 6월 1일 시행된 시행규칙의 위험성평가 관련 조문에 따라 근로자 참여, 유해·위험요인 파악, 위험성 결정, 감소대책 수립·이행과 결과 공유를 수행한다. 현행 시행규칙 체계에서 제37조는 방법·절차·시기, 제37조의2는 근로자 참여, 제37조의3은 근로자 공유, 제37조의4는 결과의 기록·보존을 규정한다. 제37조의4에 따라 실시 시기·담당자, 참여한 근로자·근로자대표, 실시 후 근로자에게 공유한 사항 등을 기록하고 관련 자료를 3년간 보존한다. 구체 평가 시기와 변경·사고 시 요건은 최신 시행규칙과 「사업장 위험성평가에 관한 지침」을 함께 확인한다.","type":"paragraph"}],"id":"notion-f1d386d0c8c0ea77","schemaVersion":1,"sourcePath":"Notion page 39902e78-962a-8051-8275-d4d91a78e607 › 제2편 용접 및 안전관리 › 제2장 용접 시공 › 4. 안전관리 › 4.1 위험성평가와 통제 원칙","title":"4.1 위험성평가와 통제 원칙"}