{"blocks":[{"text":"기계요소 보전은 고장 부품을 교환하는 데서 끝나지 않고 기능 기준을 회복하고 재발 원인을 제거하는 활동이다.","type":"paragraph"},{"items":["안전정지, 잔류에너지 해소, 잠금·표찰(LOTO)을 실시한다.","운전자가 느낀 소음·냄새·진동·온도·발생 시점을 확인한다.","정상 기준값과 현재값을 비교하고 변화 추세를 본다.","하중·속도·정렬·윤활·오염·체결·온도 순으로 원인 가설을 세운다.","비파괴 계측 후 필요한 범위만 분해한다. 분해 전 위치와 방향을 표시하고 사진·치수를 기록한다.","고장부품뿐 아니라 상대부품, 윤활계통, 보호장치, 운전조건을 함께 점검한다.","조립 후 손회전, 무부하, 단계 부하 시운전과 누설·진동·온도 확인을 한다.","원인, 조치, 교환품, 측정값, 재발방지 대책을 이력으로 남긴다."],"ordered":true,"type":"list"}],"id":"notion-34a6b0742663cda7","schemaVersion":1,"sourcePath":"Notion page 39902e78-962a-8051-8275-d4d91a78e607 › 제3편 기계 설계 일반 › 제6장 기계 장치 보전 › 1. 기계 요소 보전 › 1.1 보전의 기본 절차","title":"1.1 보전의 기본 절차"}