{"blocks":[{"text":"직류에서는 용접 케이블 연결에 따라 극성이 정해진다.","type":"paragraph"},{"items":["DCEN(직류 정극성): 전극이 음극(-), 모재가 양극(+)이다.","DCEP(직류 역극성): 전극이 양극(+), 모재가 음극(-)이다.","AC(교류): 반주기마다 극성이 바뀐다."],"ordered":false,"type":"list"},{"text":"고전적인 아크 설명에서는 양극 쪽 발열이 큰 것으로 배우지만, 실제 용입·전극용융·산화막 제거는 전극 재질, 보호가스, 전류 파형과 공정에 따라 달라진다. 예를 들어 GMAW는 일반적으로 DCEP를 사용하여 안정된 금속이행을 얻고, 탄소강 GTAW는 흔히 DCEN을 쓴다. 알루미늄 GTAW의 AC는 전극 음극 반주기의 용입 효과와 전극 양극 반주기의 산화막 청정작용을 조합한다. 시험에서도 “모든 공정에서 DCEP가 무조건 깊은 용입”처럼 절대화하지 말고 공정 조건을 본다. 아크 쏠림(arc blow)은 용접전류가 만든 자기장이 비대칭이어서 아크가 진행 방향 또는 옆으로 휘는 현상이다. 직류, 자성체, 부재 모서리와 이음 끝, 큰 전류에서 두드러진다. 짧은 아크 유지, 전류 감소, 교류 사용, 접지 위치·전류 경로·용접 순서 변경, 엔드탭 사용, 전극 각도 조정으로 완화한다. 접지점을 무조건 가깝게 또는 멀리 두는 것이 아니라 자기장과 전류 귀로를 바꾸는 것이 핵심이다.","type":"paragraph"}],"id":"notion-e74d160f592590cc","schemaVersion":1,"sourcePath":"Notion page 39902e78-962a-8051-8275-d4d91a78e607 › 제2편 용접 및 안전관리 › 제1장 용접 일반 이론 › 1. 아크 용접 › 1.4 극성, 아크 쏠림과 전원 선택","title":"1.4 극성, 아크 쏠림과 전원 선택"}