{"blocks":[{"alt":"Notion 원문 이미지","caption":"Notion 원문 이미지","rightsStatus":"unknown","src":"","type":"image"},{"text":"실물 판별: 본체 위를 가로지르는 언더바(요크)에 베어링 내경을 끼우고, 온도센서는 내륜에 밀착한다. 가열 후에는 장비 지침에 따라 탈자하고 방열장갑으로 즉시 조립한다.","type":"quote"},{"text":"*사진·라이선스: Betex BLF 201 bearing induction heater — Wikimedia Commons*.JPG)*, © S.J. de Waard / CC BY-SA 4.0.*","type":"paragraph"},{"items":["베어링 내경에 맞는 언더바(요크)를 선택한다.","베어링을 언더바에 끼워 가열기에 설치한다.","온도센서를 베어링 내륜에 밀착시킨다.","목표 가열온도를 설정하고 가열을 시작한다.","설정온도에 도달하면 가열을 멈추고 탈자 기능이 있는 장비는 제조사 순서대로 탈자한다.","방열장갑을 착용해 베어링을 꺼낸다.","지체 없이 축의 어깨까지 바르게 삽입하고 자연 냉각시킨다."],"ordered":true,"type":"list"},{"text":"함정: 온도센서를 외륜이나 공중에 두면 내륜 실제온도를 놓칠 수 있다. 화염으로 국부가열하거나 제조사 제한온도를 넘기지 않으며, 가열 중 실·그리스·열처리 조직이 손상되지 않도록 한다. 가열 조립은 내륜을 균일하게 팽창시키는 방법이지 구름요소를 통해 억지로 두드리는 작업이 아니다. *대조 원문: 운반하역기계 구동장치 정비 NCS* 하중 방향에 대해 회전하는 궤도륜에는 크리프 방지를 위해 일반적으로 억지 끼워맞춤을 검토한다. 고정하중을 받는 궤도륜은 조립성과 열팽창을 고려해 더 느슨한 끼워맞춤이 가능할 수 있다. 정확한 공차는 하중, 크기, 재질, 온도, 축방향 이동 요구와 제조사 표를 따른다. 내부간극은 조립 억지량과 운전 온도차로 감소할 수 있다. 예압은 강성과 회전정밀도를 높이지만 과도하면 발열과 수명저하를 일으킨다. 그리스는 취급과 밀봉이 쉽고, 오일은 고속·고온에서 냉각과 순환여과에 유리할 수 있다. 그리스 충전량은 빈 공간을 무조건 가득 채우지 않고 속도·공간·제조사 지침에 따른다. 방사 내부간극의 보통급은 흔히 CN으로 표시하고, C2는 그보다 작고 C3·C4는 더 큰 간극 계열이다. C3를 곧 ‘마모된 헐거운 베어링’으로 해석하지 말고 억지 끼워맞춤과 운전온도에서 필요한 실제 운전간극을 맞추기 위한 선택으로 본다. 앵귤러 콘택트나 테이퍼롤러베어링의 정위치 예압은 스페이서·너트 등으로 축방향 상대 위치를 정해 예압을 주고, 정압(일정압) 예압은 스프링 등으로 비교적 일정한 힘을 유지한다. 전자는 강성이 높고 후자는 열팽창·변위 흡수에 유리할 수 있다. 베어링은 힘을 구름요소에 전달하지 않도록 장착한다. 축에 내륜을 끼울 때는 내륜에, 하우징에 외륜을 끼울 때는 외륜에 힘을 가한다. 분리형이 아니면 구름요소를 통해 압입력을 전달하지 않는다.","type":"paragraph"}],"id":"notion-408fc2ab6dee4693","schemaVersion":1,"sourcePath":"Notion page 39902e78-962a-8051-8275-d4d91a78e607 › 제3편 기계 설계 일반 › 제5장 기계 구동 장치 조립 › 1. 기계 구동 장치 조립 › 최근 기출 연결·변형 대비｜유도가열기 작업 순서 › 📷 웹 실사 보강｜베어링 유도가열기","title":"📷 웹 실사 보강｜베어링 유도가열기"}