{"blocks":[{"text":"도체 단면적은 허용전류만이 아니라 전압강하, 단락 시 열적 내량, 포설 방식, 주위온도, 집합배선, 기계적 강도를 고려해 정한다. 색상과 식별은 현행 규정 및 사업장 표준을 따른다.","type":"paragraph"},{"items":["피복은 심선을 손상하지 않도록 정해진 길이만 벗긴다.","압착단자는 전선 굵기·단자 형식에 맞는 공구와 다이스를 사용하고, 완전 삽입 후 규정 위치를 압착한다.","압착 후 심선 빠짐, 절연칼라 손상, 과다 노출, 압착 높이 이상을 확인한다. 중요 접속은 작업 표준의 인장·외관 기준을 따른다.","나사 단자는 지정 토크로 조인다. 지나친 토크는 나사·단자를 손상하고, 부족 토크는 접촉저항과 발열을 키운다.","연선 끝을 납땜해 나사 단자에 물리는 방식은 크리프와 풀림 문제를 일으킬 수 있으므로 제조사 허용 여부를 확인하고 일반적으로 적합한 페룰을 사용한다.","납땜은 모재 가열, 젖음성, 플럭스 잔류, 냉땜·과열을 관리한다. 민감한 반도체에는 정전기 방전(ESD) 대책을 쓴다."],"ordered":false,"type":"list"}],"id":"notion-38bc8092d3952e68","schemaVersion":1,"sourcePath":"Notion page 39902e78-962a-8051-8275-d4d91a78e607 › 제1편 공유압 및 자동 제어 › 제2장 전기 전자 장치 조립 › 1. 전기 전자 장치 조립 › 2) 전선·단자·접속","title":"2) 전선·단자·접속"}