{"blocks":[{"items":["강도: 외력에 파괴되거나 과도하게 변형되지 않고 견디는 능력.","경도: 압입, 긁힘, 마모 등에 저항하는 성질.","탄성: 하중을 제거하면 원래 형상으로 돌아가는 성질.","소성: 하중을 제거해도 영구변형이 남는 성질.","연성: 인장하중에서 길게 늘어날 수 있는 성질.","전성: 압축하중에서 넓게 퍼질 수 있는 성질.","인성: 파괴까지 에너지를 흡수하는 능력.","취성: 소성변형이 작고 갑자기 파괴되는 성질.","피로: 반복응력으로 정적 강도보다 낮은 응력에서도 균열이 시작·성장하여 파괴되는 현상.","크리프: 주로 고온에서 일정 응력이 장시간 작용할 때 시간에 따라 변형이 증가하는 현상."],"ordered":false,"type":"list"},{"text":"인장·압축의 공칭응력과 공칭변형률은 $$ \\sigma=\\frac{F}{A_0}\\;[\\mathrm{Pa}],\\qquad \\varepsilon=\\frac{L-L_0}{L_0} $$ 이다. 탄성구간에서는 훅의 법칙 $\\sigma=E\\varepsilon$로 나타내며 $E$는 종탄성계수(Pa)다. 전단에서는 $\\tau=F/A$, $\\tau=G\\gamma$를 사용한다. 인장시험 곡선에서 비례한도, 탄성한도, 항복강도, 인장강도, 파단을 구분한다. 명확한 항복점이 없는 재료는 규정된 영구변형률의 오프셋 항복강도를 사용할 수 있다.","type":"paragraph"}],"id":"notion-9aa080fea273c40f","schemaVersion":1,"sourcePath":"Notion page 39902e78-962a-8051-8275-d4d91a78e607 › 제3편 기계 설계 일반 › 제4장 기계 재료 › 1. 기계 재료의 성질과 분류 › 1.1 기계적 성질과 응력·변형률","title":"1.1 기계적 성질과 응력·변형률"}